README.rst
setup.cfg
setup.py
always_authenticated/__init__.py
always_authenticated/middleware.py
django_always_authenticated.egg-info/PKG-INFO
django_always_authenticated.egg-info/SOURCES.txt
django_always_authenticated.egg-info/dependency_links.txt
django_always_authenticated.egg-info/top_level.txt