Metadata-Version: 1.1
Name: django-always-authenticated
Version: 0.1.0
Summary: A Django middleware that ensures every request has anauthenticated user.
Home-page: https://github.com/dhepper/django-always-authenticated
Author: Daniel Hepper
Author-email: daniel@hepper.net
License: Simplified BSD License
Platform: UNKNOWN
Classifier: Environment :: Web Environment
Classifier: Framework :: Django
Classifier: Intended Audience :: Developers
Classifier: License :: OSI Approved :: BSD License
Classifier: Operating System :: OS Independent
Classifier: Programming Language :: Python
Classifier: Programming Language :: Python :: 2.7
Classifier: Programming Language :: Python :: 3
Classifier: Programming Language :: Python :: 3.4
Classifier: Programming Language :: Python :: 3.5
Classifier: Topic :: Internet :: WWW/HTTP
Classifier: Topic :: Internet :: WWW/HTTP :: Dynamic Content
